{
  "frame": {
    "name": "Am i Based",
    "version": "1",
    "iconUrl": "https://am-i-based.vercel.app/icon.png",
    "homeUrl": "https://am-i-based.vercel.app",
    "imageUrl": "https://am-i-based.vercel.app/image.png",
    "buttonTitle": "Check your aura",
    "splashImageUrl": "https://am-i-based.vercel.app/splash.png",
    "splashBackgroundColor": "#0b0b0b",
    "webhookUrl": "https://am-i-based.vercel.app/api/webhook",
    "subtitle": "Check your onchain aura",
    "description": "Analyze your wallet on Base and discover how based you really are. Pay once, get your score, and flex the result.",
    "screenshotUrls": [
      "https://am-i-based.vercel.app/screenshot1.png"
    ],
    "primaryCategory": "finance",
    "tags": [
      "base",
      "wallet",
      "onchain",
      "based",
      "analyzis"
    ],
    "heroImageUrl": "https://am-i-based.vercel.app/hero.png",
    "tagline": "Stay based. Keep apeing.",
    "ogTitle": "Am I Based?",
    "ogDescription": "Check your onchain aura on Base. Stay based.",
    "ogImageUrl": "https://am-i-based.vercel.app/og-image.png"
  },
  "accountAssociation": {
    "header": "eyJmaWQiOjE1MjI1NjMsInR5cGUiOiJhdXRoIiwia2V5IjoiMHg3MWRiZjdhNTBlRkU0OTYyOTc2OGRjOGExNEZCMEIyYjdjZTRGZjJjIn0",
    "payload": "eyJkb21haW4iOiJhbS1pLWJhc2VkLnZlcmNlbC5hcHAifQ",
    "signature": "I7XP1V2mzcm6+PoA7RR2GfUsVQCLGylZblH7OJ1jlkkiPBD51gxPvCff+AQGiY2xvr1QbDfrVHXV0fSNx+kWHRs="
  }
}
